setup.py
mozhttpd/__init__.py
mozhttpd/handlers.py
mozhttpd/iface.py
mozhttpd/mozhttpd.py
mozhttpd.egg-info/PKG-INFO
mozhttpd.egg-info/SOURCES.txt
mozhttpd.egg-info/dependency_links.txt
mozhttpd.egg-info/entry_points.txt
mozhttpd.egg-info/not-zip-safe
mozhttpd.egg-info/top_level.txt