Metadata-Version: 1.0
Name: mozhttpd
Version: 0.3
Summary: basic python webserver, tested with talos
Home-page: https://github.com/mozilla/mozbase/tree/master/mozhttpd
Author: Joel Maher
Author-email: tools@lists.mozilla.org
License: MPL
Keywords: mozilla
Platform: UNKNOWN
